README
setup.cfg
setup.py
djio/__init__.py
djio/errors.py
djio/geometry.py
djio/hashing.py
djio.egg-info/PKG-INFO
djio.egg-info/SOURCES.txt
djio.egg-info/dependency_links.txt
djio.egg-info/requires.txt
djio.egg-info/top_level.txt