Metadata-Version: 1.2
Name: djio
Version: 0.0.3
Summary: Djiographic Information Systems
Home-page: http://djio.readthedocs.io/en/latest/index.html
Author: Pat Daburu
Author-email: pat@daburu.net
License: MIT
Download-URL: https://github.com/pblair/ploogz/archive/0.0.3.tar.gz
Keywords: GIS
Platform: UNKNOWN
Classifier: Development Status :: 3 - Alpha
Classifier: Intended Audience :: Developers
Classifier: Topic :: Software Development :: Libraries
Classifier: License :: OSI Approved :: MIT License
Classifier: Programming Language :: Python :: 3.6
Requires-Python: >=3.6.1
